nwswx/__init__.py
nwswx/__version__.py
nwswx/api.py
nwswx/client.py
nwswx/exceptions.py
nwswx/format_types.py
nwswx-0.1.2.dist-info/LICENSE
nwswx-0.1.2.dist-info/METADATA
nwswx-0.1.2.dist-info/WHEEL
nwswx-0.1.2.dist-info/top_level.txt
nwswx-0.1.2.dist-info/RECORD
