Metadata-Version: 2.1
Name: nwswx
Version: 0.1.2
Summary: A Python 3 client for retrieving data from the NWS Weather Forecast API
Home-page: https://github.com/stacybrock/nwswx
Author: Stacy Brock
Author-email: kalrnux@gmail.com
License: Apache-2.0
Classifier: Development Status :: 2 - Pre-Alpha
Classifier: License :: OSI Approved :: Apache Software License
Classifier: Programming Language :: Python
Classifier: Programming Language :: Python :: 3
Classifier: Programming Language :: Python :: 3.6
Classifier: Programming Language :: Python :: 3.7
Classifier: Programming Language :: Python :: 3.8
Classifier: Programming Language :: Python :: 3.9
Classifier: Programming Language :: Python :: 3.10
Classifier: Programming Language :: Python :: 3.11
Requires-Python: >=3.6.0
License-File: LICENSE
Requires-Dist: requests
